README.md
setup.cfg
setup.py
fastdl/__init__.py
fastdl/__version__.py
fastdl/config.py
fastdl/downloader.py
fastdl/extractor.py
fastdl/hasher.py
fastdl/parallel.py
fastdl/utils.py
fastdl.egg-info/PKG-INFO
fastdl.egg-info/SOURCES.txt
fastdl.egg-info/dependency_links.txt
fastdl.egg-info/requires.txt
fastdl.egg-info/top_level.txt