Metadata-Version: 2.1
Name: fastdl
Version: 0.1.3
Summary: Download and extract files fast and easily
Home-page: https://github.com/r-salas/fastdl
Author: Rubén Salas
License: MIT License
Keywords: download,parallel,http
Platform: UNKNOWN
Classifier: Programming Language :: Python :: 3
Classifier: Operating System :: OS Independent
Classifier: Intended Audience :: Developers
Requires-Python: >=3.5
